aws_cdk/aws_autoscaling_api/__init__.py
aws_cdk/aws_autoscaling_api/py.typed
aws_cdk/aws_autoscaling_api/_jsii/__init__.py
aws_cdk/aws_autoscaling_api/_jsii/aws-autoscaling-api@0.32.0.jsii.tgz
aws_cdk.aws_autoscaling_api-0.32.0.dist-info/METADATA
aws_cdk.aws_autoscaling_api-0.32.0.dist-info/WHEEL
aws_cdk.aws_autoscaling_api-0.32.0.dist-info/top_level.txt
aws_cdk.aws_autoscaling_api-0.32.0.dist-info/RECORD
