Metadata-Version: 2.1
Name: aws-cdk.aws-autoscaling-api
Version: 0.32.0
Summary: API package for @aws-cdk/aws-autoscaling
Home-page: https://github.com/awslabs/aws-cdk
Author: Amazon Web Services
License: UNKNOWN
Project-URL: Source, https://github.com/awslabs/aws-cdk.git
Platform: UNKNOWN
Requires-Python: >=3.6
Requires-Dist: jsii (~=0.11.0)
Requires-Dist: publication (>=0.0.3)
Requires-Dist: aws-cdk.aws-iam (~=0.32.0)
Requires-Dist: aws-cdk.cdk (~=0.32.0)
